[{"id":110763322,"user_id":78,"value":40.0,"unit":"cpm","location_name":null,"device_id":null,"original_id":null,"measurement_import_id":35385,"captured_at":"2018-04-25T02:26:52.000Z","height":null,"devicetype_id":null,"sensor_id":null,"station_id":null,"channel_id":null,"latitude":37.47538,"longitude":139.81732833333334},{"id":110763323,"user_id":78,"value":37.0,"unit":"cpm","location_name":null,"device_id":null,"original_id":null,"measurement_import_id":35385,"captured_at":"2018-04-25T02:26:47.000Z","height":null,"devicetype_id":null,"sensor_id":null,"station_id":null,"channel_id":null,"latitude":37.47538,"longitude":139.81732833333334},{"id":110763324,"user_id":78,"value":40.0,"unit":"cpm","location_name":null,"device_id":null,"original_id":null,"measurement_import_id":35385,"captured_at":"2018-04-25T02:26:42.000Z","height":null,"devicetype_id":null,"sensor_id":null,"station_id":null,"channel_id":null,"latitude":37.47538,"longitude":139.81732833333334},{"id":110763325,"user_id":78,"value":41.0,"unit":"cpm","location_name":null,"device_id":null,"original_id":null,"measurement_import_id":35385,"captured_at":"2018-04-25T02:26:37.000Z","height":null,"devicetype_id":null,"sensor_id":null,"station_id":null,"channel_id":null,"latitude":37.47538,"longitude":139.81732666666667},{"id":110763326,"user_id":78,"value":42.0,"unit":"cpm","location_name":null,"device_id":null,"original_id":null,"measurement_import_id":35385,"captured_at":"2018-04-25T02:26:32.000Z","height":null,"devicetype_id":null,"sensor_id":null,"station_id":null,"channel_id":null,"latitude":37.47538,"longitude":139.81732666666667},{"id":110763327,"user_id":78,"value":38.0,"unit":"cpm","location_name":null,"device_id":null,"original_id":null,"measurement_import_id":35385,"captured_at":"2018-04-25T02:26:27.000Z","height":null,"devicetype_id":null,"sensor_id":null,"station_id":null,"channel_id":null,"latitude":37.47538,"longitude":139.81732666666667},{"id":110763328,"user_id":78,"value":37.0,"unit":"cpm","location_name":null,"device_id":null,"original_id":null,"measurement_import_id":35385,"captured_at":"2018-04-25T02:26:22.000Z","height":null,"devicetype_id":null,"sensor_id":null,"station_id":null,"channel_id":null,"latitude":37.47538,"longitude":139.81732666666667},{"id":110763329,"user_id":78,"value":32.0,"unit":"cpm","location_name":null,"device_id":null,"original_id":null,"measurement_import_id":35385,"captured_at":"2018-04-25T02:26:16.000Z","height":null,"devicetype_id":null,"sensor_id":null,"station_id":null,"channel_id":null,"latitude":37.47538,"longitude":139.81732666666667},{"id":110763330,"user_id":78,"value":36.0,"unit":"cpm","location_name":null,"device_id":null,"original_id":null,"measurement_import_id":35385,"captured_at":"2018-04-25T02:26:11.000Z","height":null,"devicetype_id":null,"sensor_id":null,"station_id":null,"channel_id":null,"latitude":37.47538,"longitude":139.81732666666667},{"id":110763331,"user_id":78,"value":40.0,"unit":"cpm","location_name":null,"device_id":null,"original_id":null,"measurement_import_id":35385,"captured_at":"2018-04-25T02:26:06.000Z","height":null,"devicetype_id":null,"sensor_id":null,"station_id":null,"channel_id":null,"latitude":37.47538,"longitude":139.81732666666667},{"id":110763332,"user_id":78,"value":40.0,"unit":"cpm","location_name":null,"device_id":null,"original_id":null,"measurement_import_id":35385,"captured_at":"2018-04-25T02:26:01.000Z","height":null,"devicetype_id":null,"sensor_id":null,"station_id":null,"channel_id":null,"latitude":37.47538,"longitude":139.81732666666667},{"id":110763333,"user_id":78,"value":40.0,"unit":"cpm","location_name":null,"device_id":null,"original_id":null,"measurement_import_id":35385,"captured_at":"2018-04-25T02:25:56.000Z","height":null,"devicetype_id":null,"sensor_id":null,"station_id":null,"channel_id":null,"latitude":37.47538,"longitude":139.81732666666667},{"id":110763334,"user_id":78,"value":43.0,"unit":"cpm","location_name":null,"device_id":null,"original_id":null,"measurement_import_id":35385,"captured_at":"2018-04-25T02:25:51.000Z","height":null,"devicetype_id":null,"sensor_id":null,"station_id":null,"channel_id":null,"latitude":37.47538,"longitude":139.81732666666667},{"id":110763335,"user_id":78,"value":45.0,"unit":"cpm","location_name":null,"device_id":null,"original_id":null,"measurement_import_id":35385,"captured_at":"2018-04-25T02:25:46.000Z","height":null,"devicetype_id":null,"sensor_id":null,"station_id":null,"channel_id":null,"latitude":37.47538,"longitude":139.81732666666667},{"id":110763336,"user_id":78,"value":44.0,"unit":"cpm","location_name":null,"device_id":null,"original_id":null,"measurement_import_id":35385,"captured_at":"2018-04-25T02:25:41.000Z","height":null,"devicetype_id":null,"sensor_id":null,"station_id":null,"channel_id":null,"latitude":37.47538,"longitude":139.81732666666667},{"id":110763337,"user_id":78,"value":42.0,"unit":"cpm","location_name":null,"device_id":null,"original_id":null,"measurement_import_id":35385,"captured_at":"2018-04-25T02:25:35.000Z","height":null,"devicetype_id":null,"sensor_id":null,"station_id":null,"channel_id":null,"latitude":37.47538,"longitude":139.817325},{"id":110763338,"user_id":78,"value":41.0,"unit":"cpm","location_name":null,"device_id":null,"original_id":null,"measurement_import_id":35385,"captured_at":"2018-04-25T02:25:30.000Z","height":null,"devicetype_id":null,"sensor_id":null,"station_id":null,"channel_id":null,"latitude":37.47538,"longitude":139.817325},{"id":110763339,"user_id":78,"value":43.0,"unit":"cpm","location_name":null,"device_id":null,"original_id":null,"measurement_import_id":35385,"captured_at":"2018-04-25T02:25:25.000Z","height":null,"devicetype_id":null,"sensor_id":null,"station_id":null,"channel_id":null,"latitude":37.47538,"longitude":139.817325},{"id":110763340,"user_id":78,"value":46.0,"unit":"cpm","location_name":null,"device_id":null,"original_id":null,"measurement_import_id":35385,"captured_at":"2018-04-25T02:25:20.000Z","height":null,"devicetype_id":null,"sensor_id":null,"station_id":null,"channel_id":null,"latitude":37.47538,"longitude":139.817325},{"id":110763341,"user_id":78,"value":45.0,"unit":"cpm","location_name":null,"device_id":null,"original_id":null,"measurement_import_id":35385,"captured_at":"2018-04-25T02:25:15.000Z","height":null,"devicetype_id":null,"sensor_id":null,"station_id":null,"channel_id":null,"latitude":37.47538,"longitude":139.817325},{"id":110763342,"user_id":78,"value":42.0,"unit":"cpm","location_name":null,"device_id":null,"original_id":null,"measurement_import_id":35385,"captured_at":"2018-04-25T02:25:10.000Z","height":null,"devicetype_id":null,"sensor_id":null,"station_id":null,"channel_id":null,"latitude":37.47538,"longitude":139.817325},{"id":110763343,"user_id":78,"value":36.0,"unit":"cpm","location_name":null,"device_id":null,"original_id":null,"measurement_import_id":35385,"captured_at":"2018-04-25T02:25:05.000Z","height":null,"devicetype_id":null,"sensor_id":null,"station_id":null,"channel_id":null,"latitude":37.47538,"longitude":139.817325},{"id":110763344,"user_id":78,"value":38.0,"unit":"cpm","location_name":null,"device_id":null,"original_id":null,"measurement_import_id":35385,"captured_at":"2018-04-25T02:25:00.000Z","height":null,"devicetype_id":null,"sensor_id":null,"station_id":null,"channel_id":null,"latitude":37.47538,"longitude":139.817325},{"id":110763345,"user_id":78,"value":36.0,"unit":"cpm","location_name":null,"device_id":null,"original_id":null,"measurement_import_id":35385,"captured_at":"2018-04-25T02:24:55.000Z","height":null,"devicetype_id":null,"sensor_id":null,"station_id":null,"channel_id":null,"latitude":37.47538,"longitude":139.817325},{"id":110763346,"user_id":78,"value":33.0,"unit":"cpm","location_name":null,"device_id":null,"original_id":null,"measurement_import_id":35385,"captured_at":"2018-04-25T02:24:50.000Z","height":null,"devicetype_id":null,"sensor_id":null,"station_id":null,"channel_id":null,"latitude":37.47538,"longitude":139.81732333333332}]