{
  "schema": "SEAM_RECURSIVE_OPERATIONAL_STATE",
  "version": "1.5",
  "generated_utc": "2026-05-14T07:31:10.092725+00:00",
  "source_field": "combined\\seam_unified_recursive_field_48h.json",
  "convergence": {
    "mode": "recursive_transitive_restored",
    "score_threshold": 0.58,
    "strong_distance_km": 18.0,
    "weak_distance_km": 45.0,
    "time_chain_hours": 8.0,
    "seed_count": 2330,
    "canonical_count": 7
  },
  "event_count": 7,
  "active_event_count": 2,
  "events": [
    {
      "event_id": "MANI-062324-0006",
      "event_family": "SEAM_RECURSIVE_MANIFOLD",
      "acquisition_utc": "2024-06-23T08:27:25.722409+00:00",
      "first_observation_utc": "2024-06-23T08:27:25.722409+00:00",
      "last_observation_utc": "2026-05-14T07:29:38.112581+00:00",
      "pred_time_utc": "2024-06-23T08:48:25.722409+00:00",
      "lock_state": "FOLLOW PROTOCOL (63.6%)",
      "recursive_lock": 63.6,
      "lock_thresholds": {
        "85_percent_utc": null,
        "90_percent_utc": null,
        "95_percent_utc": null
      },
      "lock_progression_seconds": {
        "85_to_90": null,
        "90_to_95": null,
        "85_to_official": null
      },
      "signature": "Crustal Pulse",
      "signature_family": "SEISMIC",
      "signature_subclass": "Recursive Coupled Perturbation",
      "regime": "seismic",
      "magnitude": "M 7.4",
      "location": {
        "country": "United States",
        "state_region": "CA",
        "county_area": "Texas / New Mexico Region",
        "city": "Redlands",
        "locality": "Redlands, CA",
        "street_cross": "6 km SSW of Redlands, CA",
        "display_follow": "Texas / New Mexico Region",
        "display_target": "Redlands, CA, United States",
        "display_lock": "Redlands, CA | 34.8050, -96.2827",
        "lat_long": "34.8050, -96.2827",
        "location_precision": "area",
        "location_source": "payload"
      },
      "street_cross": "6 km SSW of Redlands, CA",
      "display_location": "Redlands, CA, United States",
      "latitude": 34.805,
      "longitude": -96.2827,
      "lat_long": "34.8050, -96.2827",
      "course": "SW drift",
      "spatial_region": "Texas / New Mexico Region",
      "observation_count": 8092,
      "source_count": 6,
      "sources": [
        "EMSC",
        "IRIS",
        "RaspberryShake",
        "Safecast",
        "SatNOGS",
        "USGS"
      ],
      "evidence_summary": [
        "Recursive manifold density detected",
        "Temporal coherence preserved",
        "Spatial clustering present"
      ],
      "contradictions": [],
      "_convergence_passes": 2,
      "lock_direction": "\u2192",
      "lock_velocity_per_minute": null,
      "detector_count": null,
      "persistence_state": {
        "active_duration_seconds": 59612532,
        "persistence_score": 1.0,
        "trajectory_stability": 0.64,
        "field_viability": "TRANSIENT"
      },
      "verification_state": {
        "official_confirmation": false,
        "official_source": null,
        "official_record_id": null,
        "official_classification": null,
        "official_timestamp_utc": null,
        "lead_time_seconds": null,
        "magnitude_delta": null,
        "spatial_error_km": null,
        "classification_agreement": null
      },
      "cross_regime_couplings": [],
      "manifold_topology": {
        "topology_class": "Localized Recursive Compression",
        "field_density": 0.64,
        "cross_regime_density": 0.25,
        "recursive_complexity": 1.0
      },
      "estimated_energy": {
        "value": null,
        "units": "joules"
      },
      "altitude_km": null,
      "depth_km": null,
      "velocity_vector": {
        "bearing_degrees": null,
        "velocity_kmh": null
      },
      "source_lineage": [],
      "linked_observations": [
        "OBS-00000077",
        "OBS-00000127",
        "OBS-00000179",
        "OBS-00000230",
        "OBS-00000280",
        "OBS-00000330",
        "OBS-00000380",
        "OBS-00000430",
        "OBS-00000480",
        "OBS-00000530",
        "OBS-00000580",
        "OBS-00000630",
        "OBS-00000681",
        "OBS-00037324",
        "OBS-00037374",
        "OBS-00037426",
        "OBS-00037477",
        "OBS-00037527",
        "OBS-00037577",
        "OBS-00037627",
        "OBS-00037677",
        "OBS-00037727",
        "OBS-00037777",
        "OBS-00037827",
        "OBS-00037877",
        "OBS-00037928",
        "OBS-00000078",
        "OBS-00000129",
        "OBS-00000181",
        "OBS-00000232",
        "OBS-00000282",
        "OBS-00000332",
        "OBS-00000382",
        "OBS-00000432",
        "OBS-00000482",
        "OBS-00000532",
        "OBS-00000582",
        "OBS-00000632",
        "OBS-00000683",
        "OBS-00037325",
        "OBS-00037376",
        "OBS-00037428",
        "OBS-00037479",
        "OBS-00037529",
        "OBS-00037579",
        "OBS-00037629",
        "OBS-00037679",
        "OBS-00037729",
        "OBS-00037779",
        "OBS-00037829",
        "OBS-00037879",
        "OBS-00037930",
        "OBS-00000079",
        "OBS-00000130",
        "OBS-00000182",
        "OBS-00000233",
        "OBS-00000283",
        "OBS-00000333",
        "OBS-00000383",
        "OBS-00000433",
        "OBS-00000483",
        "OBS-00000533",
        "OBS-00000583",
        "OBS-00000633",
        "OBS-00000684",
        "OBS-00037326",
        "OBS-00037377",
        "OBS-00037429",
        "OBS-00037480",
        "OBS-00037530",
        "OBS-00037580",
        "OBS-00037630",
        "OBS-00037680",
        "OBS-00037730",
        "OBS-00037780",
        "OBS-00037830",
        "OBS-00037880",
        "OBS-00037931",
        "OBS-00000080",
        "OBS-00000131",
        "OBS-00000183",
        "OBS-00000234",
        "OBS-00000284",
        "OBS-00000334",
        "OBS-00000384",
        "OBS-00000434",
        "OBS-00000484",
        "OBS-00000534",
        "OBS-00000584",
        "OBS-00000634",
        "OBS-00000685",
        "OBS-00037327",
        "OBS-00037378",
        "OBS-00037430",
        "OBS-00037481",
        "OBS-00037531",
        "OBS-00037581",
        "OBS-00037631",
        "OBS-00037681",
        "OBS-00037731",
        "OBS-00037781",
        "OBS-00037831",
        "OBS-00037881",
        "OBS-00037932",
        "OBS-00000081",
        "OBS-00000132",
        "OBS-00000184",
        "OBS-00000235",
        "OBS-00000285",
        "OBS-00000335",
        "OBS-00000385",
        "OBS-00000435",
        "OBS-00000485",
        "OBS-00000535",
        "OBS-00000585",
        "OBS-00000635",
        "OBS-00000686",
        "OBS-00037328",
        "OBS-00037379",
        "OBS-00037431",
        "OBS-00037482",
        "OBS-00037532",
        "OBS-00037582",
        "OBS-00037632",
        "OBS-00037682",
        "OBS-00037732",
        "OBS-00037782",
        "OBS-00037832",
        "OBS-00037882",
        "OBS-00037933",
        "OBS-00000082",
        "OBS-00000133",
        "OBS-00000185",
        "OBS-00000236",
        "OBS-00000286",
        "OBS-00000336",
        "OBS-00000386",
        "OBS-00000436",
        "OBS-00000486",
        "OBS-00000536",
        "OBS-00000586",
        "OBS-00000636",
        "OBS-00000687",
        "OBS-00037329",
        "OBS-00037380",
        "OBS-00037432",
        "OBS-00037483",
        "OBS-00037533",
        "OBS-00037583",
        "OBS-00037633",
        "OBS-00037683",
        "OBS-00037733",
        "OBS-00037783",
        "OBS-00037833",
        "OBS-00037883",
        "OBS-00037934",
        "OBS-00000083",
        "OBS-00000134",
        "OBS-00000186",
        "OBS-00000237",
        "OBS-00000287",
        "OBS-00000337",
        "OBS-00000387",
        "OBS-00000437",
        "OBS-00000487",
        "OBS-00000537",
        "OBS-00000587",
        "OBS-00000637",
        "OBS-00000688",
        "OBS-00037330",
        "OBS-00037381",
        "OBS-00037433",
        "OBS-00037484",
        "OBS-00037534",
        "OBS-00037584",
        "OBS-00037634",
        "OBS-00037684",
        "OBS-00037734",
        "OBS-00037784",
        "OBS-00037834",
        "OBS-00037884",
        "OBS-00037935",
        "OBS-00000084",
        "OBS-00000135",
        "OBS-00000187",
        "OBS-00000238",
        "OBS-00000288",
        "OBS-00000338",
        "OBS-00000388",
        "OBS-00000438",
        "OBS-00000488",
        "OBS-00000538",
        "OBS-00000588",
        "OBS-00000638",
        "OBS-00000689",
        "OBS-00037331",
        "OBS-00037382",
        "OBS-00037434",
        "OBS-00037485",
        "OBS-00037535",
        "OBS-00037585",
        "OBS-00037635",
        "OBS-00037685",
        "OBS-00037735",
        "OBS-00037785",
        "OBS-00037835",
        "OBS-00037885",
        "OBS-00037936",
        "OBS-00000085",
        "OBS-00000137",
        "OBS-00000189",
        "OBS-00000240",
        "OBS-00000290",
        "OBS-00000340",
        "OBS-00000390",
        "OBS-00000440",
        "OBS-00000490",
        "OBS-00000540",
        "OBS-00000590",
        "OBS-00000640",
        "OBS-00000691",
        "OBS-00037332",
        "OBS-00037384",
        "OBS-00037436",
        "OBS-00037487",
        "OBS-00037537",
        "OBS-00037587",
        "OBS-00037637",
        "OBS-00037687",
        "OBS-00037737",
        "OBS-00037787",
        "OBS-00037837",
        "OBS-00037887",
        "OBS-00037938",
        "OBS-00000086",
        "OBS-00000138",
        "OBS-00000190",
        "OBS-00000241",
        "OBS-00000291",
        "OBS-00000341",
        "OBS-00000391",
        "OBS-00000441",
        "OBS-00000491",
        "OBS-00000541",
        "OBS-00000591",
        "OBS-00000641",
        "OBS-00000692",
        "OBS-00037333",
        "OBS-00037385",
        "OBS-00037437"
      ],
      "forecast_state": {
        "projection_state": "ACTIVE",
        "estimated_decay_utc": "2026-05-14T11:29:38.112581+00:00",
        "forecast_confidence": 0.64
      },
      "dashboard_priority": 63.6,
      "operational_priority": "LOW",
      "operational_notes": [
        "Monitor recursive stabilization",
        "Track cross-regime emergence"
      ]
    },
    {
      "event_id": "MANI-031421-0007",
      "event_family": "SEAM_RECURSIVE_MANIFOLD",
      "acquisition_utc": "2021-03-14T10:34:37.119920+00:00",
      "first_observation_utc": "2021-03-14T10:34:37.119920+00:00",
      "last_observation_utc": "2026-05-14T07:29:37.707894+00:00",
      "pred_time_utc": "2021-03-14T10:55:37.119920+00:00",
      "lock_state": "FOLLOW PROTOCOL (61.3%)",
      "recursive_lock": 61.3,
      "lock_thresholds": {
        "85_percent_utc": null,
        "90_percent_utc": null,
        "95_percent_utc": null
      },
      "lock_progression_seconds": {
        "85_to_90": null,
        "90_to_95": null,
        "85_to_official": null
      },
      "signature": "Radiological Drift",
      "signature_family": "RADIOLOGICAL",
      "signature_subclass": "Recursive Coupled Perturbation",
      "regime": "radiological",
      "magnitude": "106.2",
      "location": {
        "country": "Europe",
        "state_region": "Europe",
        "county_area": "Europe",
        "city": null,
        "locality": "Europe",
        "street_cross": "Europe",
        "display_follow": "Europe",
        "display_target": "Europe",
        "display_lock": "Europe | 43.1204, 38.2823",
        "lat_long": "43.1204, 38.2823",
        "location_precision": "area",
        "location_source": "coordinate_region"
      },
      "street_cross": "Europe",
      "display_location": "Europe",
      "latitude": 43.1204,
      "longitude": 38.2823,
      "lat_long": "43.1204, 38.2823",
      "course": "NW drift",
      "spatial_region": "Europe",
      "observation_count": 520,
      "source_count": 4,
      "sources": [
        "GOES",
        "NOAA_SWPC",
        "Safecast",
        "SatNOGS"
      ],
      "evidence_summary": [
        "Recursive manifold density detected",
        "Temporal coherence preserved",
        "Spatial clustering present"
      ],
      "contradictions": [],
      "_convergence_passes": 2,
      "lock_direction": "\u2192",
      "lock_velocity_per_minute": null,
      "detector_count": null,
      "persistence_state": {
        "active_duration_seconds": 163025700,
        "persistence_score": 1.0,
        "trajectory_stability": 0.61,
        "field_viability": "TRANSIENT"
      },
      "verification_state": {
        "official_confirmation": false,
        "official_source": null,
        "official_record_id": null,
        "official_classification": null,
        "official_timestamp_utc": null,
        "lead_time_seconds": null,
        "magnitude_delta": null,
        "spatial_error_km": null,
        "classification_agreement": null
      },
      "cross_regime_couplings": [],
      "manifold_topology": {
        "topology_class": "Localized Recursive Compression",
        "field_density": 0.61,
        "cross_regime_density": 0.25,
        "recursive_complexity": 0.21
      },
      "estimated_energy": {
        "value": null,
        "units": "joules"
      },
      "altitude_km": null,
      "depth_km": null,
      "velocity_vector": {
        "bearing_degrees": null,
        "velocity_kmh": null
      },
      "source_lineage": [],
      "linked_observations": [
        "OBS-00033293",
        "OBS-00033294",
        "OBS-00033295",
        "OBS-00033296",
        "OBS-00033297",
        "OBS-00033298",
        "OBS-00033299",
        "OBS-00033300",
        "OBS-00033301",
        "OBS-00033302",
        "OBS-00033303",
        "OBS-00033304",
        "OBS-00033305",
        "OBS-00033306",
        "OBS-00033307",
        "OBS-00033308",
        "OBS-00033309",
        "OBS-00033310",
        "OBS-00033311",
        "OBS-00033312",
        "OBS-00033313",
        "OBS-00033314",
        "OBS-00033315",
        "OBS-00033316",
        "OBS-00033317",
        "OBS-00033318",
        "OBS-00033319",
        "OBS-00033320",
        "OBS-00033321",
        "OBS-00033322",
        "OBS-00033323",
        "OBS-00033324",
        "OBS-00033325",
        "OBS-00033326",
        "OBS-00033327",
        "OBS-00033328",
        "OBS-00033329",
        "OBS-00033330",
        "OBS-00033331",
        "OBS-00033332",
        "OBS-00033333",
        "OBS-00033334",
        "OBS-00033335",
        "OBS-00033336",
        "OBS-00033337",
        "OBS-00033338",
        "OBS-00033339",
        "OBS-00033340",
        "OBS-00033341",
        "OBS-00033342",
        "OBS-00033343",
        "OBS-00033344",
        "OBS-00033345",
        "OBS-00033346",
        "OBS-00033347",
        "OBS-00033348",
        "OBS-00033349",
        "OBS-00033350",
        "OBS-00033351",
        "OBS-00033352",
        "OBS-00033353",
        "OBS-00033354",
        "OBS-00033355",
        "OBS-00033356",
        "OBS-00033357",
        "OBS-00033358",
        "OBS-00033359",
        "OBS-00033360",
        "OBS-00033361",
        "OBS-00033362",
        "OBS-00033363",
        "OBS-00033364",
        "OBS-00033365",
        "OBS-00033366",
        "OBS-00033367",
        "OBS-00033518",
        "OBS-00033519",
        "OBS-00033541",
        "OBS-00033520",
        "OBS-00033521",
        "OBS-00033542",
        "OBS-00033608",
        "OBS-00033522",
        "OBS-00033530",
        "OBS-00033538",
        "OBS-00033572",
        "OBS-00033580",
        "OBS-00033588",
        "OBS-00033596",
        "OBS-00033600",
        "OBS-00033601",
        "OBS-00033607",
        "OBS-00033610",
        "OBS-00033614",
        "OBS-00033523",
        "OBS-00033584",
        "OBS-00033606",
        "OBS-00033524",
        "OBS-00033526",
        "OBS-00033529",
        "OBS-00033568",
        "OBS-00033590",
        "OBS-00033611",
        "OBS-00033617",
        "OBS-00033525",
        "OBS-00033574",
        "OBS-00033527",
        "OBS-00033613",
        "OBS-00033528",
        "OBS-00033589",
        "OBS-00033615",
        "OBS-00033531",
        "OBS-00033583",
        "OBS-00033532",
        "OBS-00033535",
        "OBS-00033579",
        "OBS-00033585",
        "OBS-00033593",
        "OBS-00033533",
        "OBS-00033534",
        "OBS-00033577",
        "OBS-00033604",
        "OBS-00033536",
        "OBS-00033537",
        "OBS-00033591",
        "OBS-00033595",
        "OBS-00033539",
        "OBS-00033602",
        "OBS-00033616",
        "OBS-00033540",
        "OBS-00033543",
        "OBS-00033544",
        "OBS-00033545",
        "OBS-00033546",
        "OBS-00033547",
        "OBS-00033548",
        "OBS-00033549",
        "OBS-00033550",
        "OBS-00033551",
        "OBS-00033552",
        "OBS-00033553",
        "OBS-00033554",
        "OBS-00033555",
        "OBS-00033556",
        "OBS-00033557",
        "OBS-00033558",
        "OBS-00033559",
        "OBS-00033560",
        "OBS-00033561",
        "OBS-00033562",
        "OBS-00033563",
        "OBS-00033564",
        "OBS-00033565",
        "OBS-00033566",
        "OBS-00033567",
        "OBS-00033569",
        "OBS-00033573",
        "OBS-00033578",
        "OBS-00033599",
        "OBS-00033570",
        "OBS-00033582",
        "OBS-00033571",
        "OBS-00033576",
        "OBS-00033592",
        "OBS-00033575",
        "OBS-00033587",
        "OBS-00033603",
        "OBS-00033581",
        "OBS-00033586",
        "OBS-00033594",
        "OBS-00033605",
        "OBS-00033612",
        "OBS-00033597",
        "OBS-00033598",
        "OBS-00033609",
        "OBS-00038013",
        "OBS-00038028",
        "OBS-00038111",
        "OBS-00038126",
        "OBS-00038209",
        "OBS-00038224",
        "OBS-00038307",
        "OBS-00038322",
        "OBS-00038405",
        "OBS-00038420",
        "OBS-00038503",
        "OBS-00038518",
        "OBS-00038601",
        "OBS-00038616",
        "OBS-00038699",
        "OBS-00038714",
        "OBS-00038797",
        "OBS-00038812",
        "OBS-00038895",
        "OBS-00038910",
        "OBS-00038993",
        "OBS-00039008",
        "OBS-00039091",
        "OBS-00039106",
        "OBS-00039189",
        "OBS-00039204",
        "OBS-00039613",
        "OBS-00039628",
        "OBS-00039711",
        "OBS-00039726",
        "OBS-00039809",
        "OBS-00039824",
        "OBS-00039907",
        "OBS-00039922",
        "OBS-00040005",
        "OBS-00040020",
        "OBS-00040103",
        "OBS-00040118",
        "OBS-00040201",
        "OBS-00040216",
        "OBS-00040299",
        "OBS-00040314",
        "OBS-00040397",
        "OBS-00040412",
        "OBS-00040495",
        "OBS-00040510",
        "OBS-00040593",
        "OBS-00040608",
        "OBS-00040691",
        "OBS-00040706",
        "OBS-00040789",
        "OBS-00040804",
        "OBS-00041154",
        "OBS-00046013",
        "OBS-00050872",
        "OBS-00055731",
        "OBS-00060590",
        "OBS-00065449",
        "OBS-00070308",
        "OBS-00075167",
        "OBS-00080026",
        "OBS-00084885",
        "OBS-00089744",
        "OBS-00094603",
        "OBS-00099462",
        "OBS-00041408",
        "OBS-00046267",
        "OBS-00051126",
        "OBS-00055985",
        "OBS-00060844",
        "OBS-00065703",
        "OBS-00070562",
        "OBS-00075421",
        "OBS-00080280",
        "OBS-00085139"
      ],
      "forecast_state": {
        "projection_state": "ACTIVE",
        "estimated_decay_utc": "2026-05-14T11:29:37.707894+00:00",
        "forecast_confidence": 0.61
      },
      "dashboard_priority": 61.3,
      "operational_priority": "LOW",
      "operational_notes": [
        "Monitor recursive stabilization",
        "Track cross-regime emergence"
      ]
    },
    {
      "event_id": "MANI-041819-0002",
      "event_family": "SEAM_RECURSIVE_MANIFOLD",
      "acquisition_utc": "2019-04-18T05:39:53.343316+00:00",
      "first_observation_utc": "2019-04-18T05:39:53.343316+00:00",
      "last_observation_utc": "2026-05-14T07:29:37.410159+00:00",
      "pred_time_utc": "2019-04-18T06:00:53.343316+00:00",
      "lock_state": "IDLE/MONITOR (47.7%)",
      "recursive_lock": 47.7,
      "lock_thresholds": {
        "85_percent_utc": null,
        "90_percent_utc": null,
        "95_percent_utc": null
      },
      "lock_progression_seconds": {
        "85_to_90": null,
        "90_to_95": null,
        "85_to_official": null
      },
      "signature": "Marine Pressure Coupling",
      "signature_family": "MARINE",
      "signature_subclass": "Recursive Coupled Perturbation",
      "regime": "marine",
      "magnitude": "N/A",
      "location": {
        "country": "Africa",
        "state_region": "Africa",
        "county_area": "Africa",
        "city": null,
        "locality": "Africa",
        "street_cross": "Africa",
        "display_follow": "Africa",
        "display_target": "Africa",
        "display_lock": "Africa | 0.0000, 0.0000",
        "lat_long": "0.0000, 0.0000",
        "location_precision": "area",
        "location_source": "coordinate_region"
      },
      "street_cross": "Africa",
      "display_location": "Africa",
      "latitude": 0.0,
      "longitude": 0.0,
      "lat_long": "0.0000, 0.0000",
      "course": "Static",
      "spatial_region": "Africa",
      "observation_count": 206,
      "source_count": 3,
      "sources": [
        "ARGO",
        "NOAA_Buoys",
        "SatNOGS"
      ],
      "evidence_summary": [
        "Recursive manifold density detected",
        "Temporal coherence preserved",
        "Spatial clustering present"
      ],
      "contradictions": [],
      "_convergence_passes": 2,
      "lock_direction": "\u2192",
      "lock_velocity_per_minute": null,
      "detector_count": null,
      "persistence_state": {
        "active_duration_seconds": 223177784,
        "persistence_score": 1.0,
        "trajectory_stability": 0.48,
        "field_viability": "TRANSIENT"
      },
      "verification_state": {
        "official_confirmation": false,
        "official_source": null,
        "official_record_id": null,
        "official_classification": null,
        "official_timestamp_utc": null,
        "lead_time_seconds": null,
        "magnitude_delta": null,
        "spatial_error_km": null,
        "classification_agreement": null
      },
      "cross_regime_couplings": [],
      "manifold_topology": {
        "topology_class": "Localized Recursive Compression",
        "field_density": 0.48,
        "cross_regime_density": 0.25,
        "recursive_complexity": 0.08
      },
      "estimated_energy": {
        "value": null,
        "units": "joules"
      },
      "altitude_km": null,
      "depth_km": null,
      "velocity_vector": {
        "bearing_degrees": null,
        "velocity_kmh": null
      },
      "source_lineage": [],
      "linked_observations": [
        "OBS-00000013",
        "OBS-00000014",
        "OBS-00000015",
        "OBS-00000016",
        "OBS-00000017",
        "OBS-00000018",
        "OBS-00000019",
        "OBS-00000020",
        "OBS-00000021",
        "OBS-00000022",
        "OBS-00000023",
        "OBS-00000024",
        "OBS-00000025",
        "OBS-00032487",
        "OBS-00032488",
        "OBS-00032489",
        "OBS-00032490",
        "OBS-00032491",
        "OBS-00032492",
        "OBS-00032493",
        "OBS-00032494",
        "OBS-00032495",
        "OBS-00032496",
        "OBS-00032497",
        "OBS-00032498",
        "OBS-00032499",
        "OBS-00033627",
        "OBS-00033628",
        "OBS-00033653",
        "OBS-00033654",
        "OBS-00033678",
        "OBS-00033679",
        "OBS-00033705",
        "OBS-00033706",
        "OBS-00033730",
        "OBS-00033731",
        "OBS-00033755",
        "OBS-00033756",
        "OBS-00033780",
        "OBS-00033781",
        "OBS-00033805",
        "OBS-00033806",
        "OBS-00033830",
        "OBS-00033831",
        "OBS-00033856",
        "OBS-00033857",
        "OBS-00033881",
        "OBS-00033882",
        "OBS-00033906",
        "OBS-00033907",
        "OBS-00037288",
        "OBS-00037289",
        "OBS-00037290",
        "OBS-00037291",
        "OBS-00037292",
        "OBS-00037293",
        "OBS-00037294",
        "OBS-00037295",
        "OBS-00037296",
        "OBS-00037297",
        "OBS-00037298",
        "OBS-00037299",
        "OBS-00037300",
        "OBS-00039561",
        "OBS-00039562",
        "OBS-00039563",
        "OBS-00039564",
        "OBS-00039565",
        "OBS-00039566",
        "OBS-00039567",
        "OBS-00039568",
        "OBS-00039569",
        "OBS-00039570",
        "OBS-00039571",
        "OBS-00039572",
        "OBS-00039573",
        "OBS-00041045",
        "OBS-00041148",
        "OBS-00045904",
        "OBS-00046007",
        "OBS-00050763",
        "OBS-00050866",
        "OBS-00055622",
        "OBS-00055725",
        "OBS-00060481",
        "OBS-00060584",
        "OBS-00065340",
        "OBS-00065443",
        "OBS-00070199",
        "OBS-00070302",
        "OBS-00075058",
        "OBS-00075161",
        "OBS-00079917",
        "OBS-00080020",
        "OBS-00084776",
        "OBS-00084879",
        "OBS-00089635",
        "OBS-00089738",
        "OBS-00094494",
        "OBS-00094597",
        "OBS-00099353",
        "OBS-00099456",
        "OBS-00041055",
        "OBS-00045914",
        "OBS-00050773",
        "OBS-00055632",
        "OBS-00060491",
        "OBS-00065350",
        "OBS-00070209",
        "OBS-00075068",
        "OBS-00079927",
        "OBS-00084786",
        "OBS-00089645",
        "OBS-00094504",
        "OBS-00099363",
        "OBS-00041106",
        "OBS-00045965",
        "OBS-00050824",
        "OBS-00055683",
        "OBS-00060542",
        "OBS-00065401",
        "OBS-00070260",
        "OBS-00075119",
        "OBS-00079978",
        "OBS-00084837",
        "OBS-00089696",
        "OBS-00094555",
        "OBS-00099414",
        "OBS-00041149",
        "OBS-00041155",
        "OBS-00046008",
        "OBS-00046014",
        "OBS-00050867",
        "OBS-00050873",
        "OBS-00055726",
        "OBS-00055732",
        "OBS-00060585",
        "OBS-00060591",
        "OBS-00065444",
        "OBS-00065450",
        "OBS-00070303",
        "OBS-00070309",
        "OBS-00075162",
        "OBS-00075168",
        "OBS-00080021",
        "OBS-00080027",
        "OBS-00084880",
        "OBS-00084886",
        "OBS-00089739",
        "OBS-00089745",
        "OBS-00094598",
        "OBS-00094604",
        "OBS-00099457",
        "OBS-00099463",
        "OBS-00041665",
        "OBS-00046524",
        "OBS-00051383",
        "OBS-00056242",
        "OBS-00061101",
        "OBS-00065960",
        "OBS-00070819",
        "OBS-00075678",
        "OBS-00080537",
        "OBS-00085396",
        "OBS-00090255",
        "OBS-00095114",
        "OBS-00099973",
        "OBS-00042244",
        "OBS-00047103",
        "OBS-00051962",
        "OBS-00056821",
        "OBS-00061680",
        "OBS-00066539",
        "OBS-00071398",
        "OBS-00076257",
        "OBS-00081116",
        "OBS-00085975",
        "OBS-00090834",
        "OBS-00095693",
        "OBS-00100552",
        "OBS-00042254",
        "OBS-00047113",
        "OBS-00051972",
        "OBS-00056831",
        "OBS-00061690",
        "OBS-00066549",
        "OBS-00071408",
        "OBS-00076267",
        "OBS-00081126",
        "OBS-00085985",
        "OBS-00090844",
        "OBS-00095703",
        "OBS-00100562",
        "OBS-00044794",
        "OBS-00049653",
        "OBS-00054512",
        "OBS-00059371",
        "OBS-00064230",
        "OBS-00069089",
        "OBS-00073948",
        "OBS-00078807",
        "OBS-00083666",
        "OBS-00088525",
        "OBS-00093384",
        "OBS-00098243",
        "OBS-00103102"
      ],
      "forecast_state": {
        "projection_state": "MONITOR",
        "estimated_decay_utc": "2026-05-14T11:29:37.410159+00:00",
        "forecast_confidence": 0.48
      },
      "dashboard_priority": 47.7,
      "operational_priority": "LOW",
      "operational_notes": [
        "Monitor recursive stabilization",
        "Track cross-regime emergence"
      ]
    },
    {
      "event_id": "MANI-042219-0001",
      "event_family": "SEAM_RECURSIVE_MANIFOLD",
      "acquisition_utc": "2019-04-22T08:22:29.502698+00:00",
      "first_observation_utc": "2019-04-22T08:22:29.502698+00:00",
      "last_observation_utc": "2026-05-14T07:29:36.155163+00:00",
      "pred_time_utc": "2019-04-22T08:43:29.502698+00:00",
      "lock_state": "IDLE/MONITOR (46.6%)",
      "recursive_lock": 46.6,
      "lock_thresholds": {
        "85_percent_utc": null,
        "90_percent_utc": null,
        "95_percent_utc": null
      },
      "lock_progression_seconds": {
        "85_to_90": null,
        "90_to_95": null,
        "85_to_official": null
      },
      "signature": "Ionospheric Coupling",
      "signature_family": "RADIO_IONOSPHERIC",
      "signature_subclass": "Recursive Coupled Perturbation",
      "regime": "radio_ionospheric",
      "magnitude": "N/A",
      "location": {
        "country": "Africa",
        "state_region": "Africa",
        "county_area": "Africa",
        "city": null,
        "locality": "Africa",
        "street_cross": "Africa",
        "display_follow": "Africa",
        "display_target": "Africa",
        "display_lock": "Africa | 0.0000, 0.0000",
        "lat_long": "0.0000, 0.0000",
        "location_precision": "area",
        "location_source": "coordinate_region"
      },
      "street_cross": "Africa",
      "display_location": "Africa",
      "latitude": 0.0,
      "longitude": 0.0,
      "lat_long": "0.0000, 0.0000",
      "course": "Static",
      "spatial_region": "Africa",
      "observation_count": 1066,
      "source_count": 7,
      "sources": [
        "AllenTelescopeArray",
        "HamSCI",
        "MITHaystack",
        "MurchisonWidefieldArray",
        "SatNOGS",
        "VLA",
        "ZooniverseRadio"
      ],
      "evidence_summary": [
        "Recursive manifold density detected",
        "Temporal coherence preserved",
        "Spatial clustering present"
      ],
      "contradictions": [],
      "_convergence_passes": 2,
      "lock_direction": "\u2192",
      "lock_velocity_per_minute": null,
      "detector_count": null,
      "persistence_state": {
        "active_duration_seconds": 222822426,
        "persistence_score": 1.0,
        "trajectory_stability": 0.47,
        "field_viability": "TRANSIENT"
      },
      "verification_state": {
        "official_confirmation": false,
        "official_source": null,
        "official_record_id": null,
        "official_classification": null,
        "official_timestamp_utc": null,
        "lead_time_seconds": null,
        "magnitude_delta": null,
        "spatial_error_km": null,
        "classification_agreement": null
      },
      "cross_regime_couplings": [],
      "manifold_topology": {
        "topology_class": "Localized Recursive Compression",
        "field_density": 0.47,
        "cross_regime_density": 0.25,
        "recursive_complexity": 0.43
      },
      "estimated_energy": {
        "value": null,
        "units": "joules"
      },
      "altitude_km": null,
      "depth_km": null,
      "velocity_vector": {
        "bearing_degrees": null,
        "velocity_kmh": null
      },
      "source_lineage": [],
      "linked_observations": [
        "OBS-00000000",
        "OBS-00000001",
        "OBS-00000002",
        "OBS-00000003",
        "OBS-00000004",
        "OBS-00000005",
        "OBS-00000006",
        "OBS-00000007",
        "OBS-00000008",
        "OBS-00000009",
        "OBS-00000010",
        "OBS-00000011",
        "OBS-00000012",
        "OBS-00032370",
        "OBS-00032371",
        "OBS-00032372",
        "OBS-00032373",
        "OBS-00032374",
        "OBS-00032375",
        "OBS-00032376",
        "OBS-00032377",
        "OBS-00032378",
        "OBS-00032379",
        "OBS-00032380",
        "OBS-00032381",
        "OBS-00032382",
        "OBS-00032448",
        "OBS-00032449",
        "OBS-00032450",
        "OBS-00032451",
        "OBS-00032452",
        "OBS-00032453",
        "OBS-00032454",
        "OBS-00032455",
        "OBS-00032456",
        "OBS-00032457",
        "OBS-00032458",
        "OBS-00032459",
        "OBS-00032460",
        "OBS-00032461",
        "OBS-00032462",
        "OBS-00032463",
        "OBS-00032464",
        "OBS-00032465",
        "OBS-00032466",
        "OBS-00032467",
        "OBS-00032468",
        "OBS-00032469",
        "OBS-00032470",
        "OBS-00032471",
        "OBS-00032472",
        "OBS-00032473",
        "OBS-00037249",
        "OBS-00037250",
        "OBS-00037251",
        "OBS-00037252",
        "OBS-00037253",
        "OBS-00037254",
        "OBS-00037255",
        "OBS-00037256",
        "OBS-00037257",
        "OBS-00037258",
        "OBS-00037259",
        "OBS-00037260",
        "OBS-00037261",
        "OBS-00037275",
        "OBS-00037276",
        "OBS-00037277",
        "OBS-00037278",
        "OBS-00037279",
        "OBS-00037280",
        "OBS-00037281",
        "OBS-00037282",
        "OBS-00037283",
        "OBS-00037284",
        "OBS-00037285",
        "OBS-00037286",
        "OBS-00037287",
        "OBS-00040889",
        "OBS-00040891",
        "OBS-00045748",
        "OBS-00045750",
        "OBS-00050607",
        "OBS-00050609",
        "OBS-00055466",
        "OBS-00055468",
        "OBS-00060325",
        "OBS-00060327",
        "OBS-00065184",
        "OBS-00065186",
        "OBS-00070043",
        "OBS-00070045",
        "OBS-00074902",
        "OBS-00074904",
        "OBS-00079761",
        "OBS-00079763",
        "OBS-00084620",
        "OBS-00084622",
        "OBS-00089479",
        "OBS-00089481",
        "OBS-00094338",
        "OBS-00094340",
        "OBS-00099197",
        "OBS-00099199",
        "OBS-00040892",
        "OBS-00045751",
        "OBS-00050610",
        "OBS-00055469",
        "OBS-00060328",
        "OBS-00065187",
        "OBS-00070046",
        "OBS-00074905",
        "OBS-00079764",
        "OBS-00084623",
        "OBS-00089482",
        "OBS-00094341",
        "OBS-00099200",
        "OBS-00040920",
        "OBS-00040921",
        "OBS-00045779",
        "OBS-00045780",
        "OBS-00050638",
        "OBS-00050639",
        "OBS-00055497",
        "OBS-00055498",
        "OBS-00060356",
        "OBS-00060357",
        "OBS-00065215",
        "OBS-00065216",
        "OBS-00070074",
        "OBS-00070075",
        "OBS-00074933",
        "OBS-00074934",
        "OBS-00079792",
        "OBS-00079793",
        "OBS-00084651",
        "OBS-00084652",
        "OBS-00089510",
        "OBS-00089511",
        "OBS-00094369",
        "OBS-00094370",
        "OBS-00099228",
        "OBS-00099229",
        "OBS-00040937",
        "OBS-00040938",
        "OBS-00040939",
        "OBS-00045796",
        "OBS-00045797",
        "OBS-00045798",
        "OBS-00050655",
        "OBS-00050656",
        "OBS-00050657",
        "OBS-00055514",
        "OBS-00055515",
        "OBS-00055516",
        "OBS-00060373",
        "OBS-00060374",
        "OBS-00060375",
        "OBS-00065232",
        "OBS-00065233",
        "OBS-00065234",
        "OBS-00070091",
        "OBS-00070092",
        "OBS-00070093",
        "OBS-00074950",
        "OBS-00074951",
        "OBS-00074952",
        "OBS-00079809",
        "OBS-00079810",
        "OBS-00079811",
        "OBS-00084668",
        "OBS-00084669",
        "OBS-00084670",
        "OBS-00089527",
        "OBS-00089528",
        "OBS-00089529",
        "OBS-00094386",
        "OBS-00094387",
        "OBS-00094388",
        "OBS-00099245",
        "OBS-00099246",
        "OBS-00099247",
        "OBS-00040958",
        "OBS-00040959",
        "OBS-00040960",
        "OBS-00045817",
        "OBS-00045818",
        "OBS-00045819",
        "OBS-00050676",
        "OBS-00050677",
        "OBS-00050678",
        "OBS-00055535",
        "OBS-00055536",
        "OBS-00055537",
        "OBS-00060394",
        "OBS-00060395",
        "OBS-00060396",
        "OBS-00065253",
        "OBS-00065254",
        "OBS-00065255",
        "OBS-00070112",
        "OBS-00070113",
        "OBS-00070114",
        "OBS-00074971",
        "OBS-00074972",
        "OBS-00074973",
        "OBS-00079830",
        "OBS-00079831",
        "OBS-00079832",
        "OBS-00084689",
        "OBS-00084690",
        "OBS-00084691",
        "OBS-00089548",
        "OBS-00089549",
        "OBS-00089550",
        "OBS-00094407",
        "OBS-00094408",
        "OBS-00094409",
        "OBS-00099266",
        "OBS-00099267",
        "OBS-00099268",
        "OBS-00040966",
        "OBS-00045825",
        "OBS-00050684",
        "OBS-00055543",
        "OBS-00060402",
        "OBS-00065261",
        "OBS-00070120",
        "OBS-00074979",
        "OBS-00079838",
        "OBS-00084697",
        "OBS-00089556",
        "OBS-00094415",
        "OBS-00099274",
        "OBS-00040971",
        "OBS-00045830",
        "OBS-00050689",
        "OBS-00055548",
        "OBS-00060407",
        "OBS-00065266",
        "OBS-00070125",
        "OBS-00074984",
        "OBS-00079843",
        "OBS-00084702",
        "OBS-00089561",
        "OBS-00094420",
        "OBS-00099279",
        "OBS-00040978",
        "OBS-00045837",
        "OBS-00050696"
      ],
      "forecast_state": {
        "projection_state": "MONITOR",
        "estimated_decay_utc": "2026-05-14T11:29:36.155163+00:00",
        "forecast_confidence": 0.47
      },
      "dashboard_priority": 46.6,
      "operational_priority": "LOW",
      "operational_notes": [
        "Monitor recursive stabilization",
        "Track cross-regime emergence"
      ]
    },
    {
      "event_id": "MANI-081523-0004",
      "event_family": "SEAM_RECURSIVE_MANIFOLD",
      "acquisition_utc": "2023-08-15T15:34:33.179219+00:00",
      "first_observation_utc": "2023-08-15T15:34:33.179219+00:00",
      "last_observation_utc": "2026-05-14T07:29:53.826737+00:00",
      "pred_time_utc": "2023-08-15T15:55:33.179219+00:00",
      "lock_state": "IDLE/MONITOR (45.1%)",
      "recursive_lock": 45.1,
      "lock_thresholds": {
        "85_percent_utc": null,
        "90_percent_utc": null,
        "95_percent_utc": null
      },
      "lock_progression_seconds": {
        "85_to_90": null,
        "90_to_95": null,
        "85_to_official": null
      },
      "signature": "Vorticity Anchor",
      "signature_family": "ATMOSPHERIC_ELECTRIC",
      "signature_subclass": "Recursive Coupled Perturbation",
      "regime": "atmospheric_electric",
      "magnitude": "N/A",
      "location": {
        "country": "Africa",
        "state_region": "Africa",
        "county_area": "Africa",
        "city": null,
        "locality": "Africa",
        "street_cross": "Africa",
        "display_follow": "Africa",
        "display_target": "Africa",
        "display_lock": "Africa | 0.0000, 0.0000",
        "lat_long": "0.0000, 0.0000",
        "location_precision": "area",
        "location_source": "coordinate_region"
      },
      "street_cross": "Africa",
      "display_location": "Africa",
      "latitude": 0.0,
      "longitude": 0.0,
      "lat_long": "0.0000, 0.0000",
      "course": "Static",
      "spatial_region": "Africa",
      "observation_count": 126,
      "source_count": 7,
      "sources": [
        "Blitzortung",
        "CWOP",
        "KiwiSDR",
        "LightningMaps",
        "ReverseBeaconNetwork",
        "SETILive",
        "SatNOGS"
      ],
      "evidence_summary": [
        "Recursive manifold density detected",
        "Temporal coherence preserved",
        "Spatial clustering present"
      ],
      "contradictions": [],
      "_convergence_passes": 2,
      "lock_direction": "\u2192",
      "lock_velocity_per_minute": null,
      "detector_count": null,
      "persistence_state": {
        "active_duration_seconds": 86630120,
        "persistence_score": 1.0,
        "trajectory_stability": 0.45,
        "field_viability": "TRANSIENT"
      },
      "verification_state": {
        "official_confirmation": false,
        "official_source": null,
        "official_record_id": null,
        "official_classification": null,
        "official_timestamp_utc": null,
        "lead_time_seconds": null,
        "magnitude_delta": null,
        "spatial_error_km": null,
        "classification_agreement": null
      },
      "cross_regime_couplings": [],
      "manifold_topology": {
        "topology_class": "Localized Recursive Compression",
        "field_density": 0.45,
        "cross_regime_density": 0.25,
        "recursive_complexity": 0.05
      },
      "estimated_energy": {
        "value": null,
        "units": "joules"
      },
      "altitude_km": null,
      "depth_km": null,
      "velocity_vector": {
        "bearing_degrees": null,
        "velocity_kmh": null
      },
      "source_lineage": [],
      "linked_observations": [
        "OBS-00000039",
        "OBS-00000040",
        "OBS-00000041",
        "OBS-00000042",
        "OBS-00000043",
        "OBS-00000044",
        "OBS-00000045",
        "OBS-00000046",
        "OBS-00000047",
        "OBS-00000048",
        "OBS-00000049",
        "OBS-00000050",
        "OBS-00000051",
        "OBS-00000052",
        "OBS-00000053",
        "OBS-00000054",
        "OBS-00000055",
        "OBS-00000056",
        "OBS-00000057",
        "OBS-00000058",
        "OBS-00000059",
        "OBS-00000060",
        "OBS-00000061",
        "OBS-00000062",
        "OBS-00000063",
        "OBS-00032396",
        "OBS-00032397",
        "OBS-00032398",
        "OBS-00032399",
        "OBS-00032400",
        "OBS-00032401",
        "OBS-00032402",
        "OBS-00032403",
        "OBS-00032404",
        "OBS-00032405",
        "OBS-00032406",
        "OBS-00032407",
        "OBS-00032408",
        "OBS-00032409",
        "OBS-00032410",
        "OBS-00032411",
        "OBS-00032412",
        "OBS-00032413",
        "OBS-00032414",
        "OBS-00032415",
        "OBS-00032416",
        "OBS-00032417",
        "OBS-00032418",
        "OBS-00032419",
        "OBS-00032420",
        "OBS-00032421",
        "OBS-00033280",
        "OBS-00033281",
        "OBS-00033282",
        "OBS-00033283",
        "OBS-00033284",
        "OBS-00033285",
        "OBS-00033286",
        "OBS-00033287",
        "OBS-00033288",
        "OBS-00033289",
        "OBS-00033290",
        "OBS-00033291",
        "OBS-00033292",
        "OBS-00037301",
        "OBS-00037302",
        "OBS-00037303",
        "OBS-00037304",
        "OBS-00037305",
        "OBS-00037306",
        "OBS-00037307",
        "OBS-00037308",
        "OBS-00037309",
        "OBS-00037310",
        "OBS-00040861",
        "OBS-00040862",
        "OBS-00040863",
        "OBS-00040864",
        "OBS-00040865",
        "OBS-00040866",
        "OBS-00040867",
        "OBS-00040868",
        "OBS-00040869",
        "OBS-00040870",
        "OBS-00040871",
        "OBS-00040872",
        "OBS-00040873",
        "OBS-00104054",
        "OBS-00104055",
        "OBS-00104056",
        "OBS-00104057",
        "OBS-00104058",
        "OBS-00104059",
        "OBS-00104060",
        "OBS-00104061",
        "OBS-00104062",
        "OBS-00104063",
        "OBS-00104064",
        "OBS-00104065",
        "OBS-00104066",
        "OBS-00043125",
        "OBS-00047984",
        "OBS-00052843",
        "OBS-00057702",
        "OBS-00062561",
        "OBS-00067420",
        "OBS-00072279",
        "OBS-00077138",
        "OBS-00081997",
        "OBS-00086856",
        "OBS-00091715",
        "OBS-00096574",
        "OBS-00101433",
        "OBS-00043857",
        "OBS-00048716",
        "OBS-00053575",
        "OBS-00058434",
        "OBS-00063293",
        "OBS-00068152",
        "OBS-00073011",
        "OBS-00077870",
        "OBS-00082729",
        "OBS-00087588",
        "OBS-00092447",
        "OBS-00097306",
        "OBS-00102165"
      ],
      "forecast_state": {
        "projection_state": "MONITOR",
        "estimated_decay_utc": "2026-05-14T11:29:53.826737+00:00",
        "forecast_confidence": 0.45
      },
      "dashboard_priority": 45.1,
      "operational_priority": "LOW",
      "operational_notes": [
        "Monitor recursive stabilization",
        "Track cross-regime emergence"
      ]
    },
    {
      "event_id": "MANI-041819-0003",
      "event_family": "SEAM_RECURSIVE_MANIFOLD",
      "acquisition_utc": "2019-04-18T05:39:53.343316+00:00",
      "first_observation_utc": "2019-04-18T05:39:53.343316+00:00",
      "last_observation_utc": "2026-05-14T07:29:37.358731+00:00",
      "pred_time_utc": "2019-04-18T06:00:53.343316+00:00",
      "lock_state": "IDLE/MONITOR (40.0%)",
      "recursive_lock": 40.0,
      "lock_thresholds": {
        "85_percent_utc": null,
        "90_percent_utc": null,
        "95_percent_utc": null
      },
      "lock_progression_seconds": {
        "85_to_90": null,
        "90_to_95": null,
        "85_to_official": null
      },
      "signature": "Recursive Field Perturbation",
      "signature_family": "UNKNOWN",
      "signature_subclass": "Recursive Coupled Perturbation",
      "regime": "unknown",
      "magnitude": "N/A",
      "location": {
        "country": "Africa",
        "state_region": "Africa",
        "county_area": "Africa",
        "city": null,
        "locality": "Africa",
        "street_cross": "Africa",
        "display_follow": "Africa",
        "display_target": "Africa",
        "display_lock": "Africa | 0.0000, 0.0000",
        "lat_long": "0.0000, 0.0000",
        "location_precision": "area",
        "location_source": "coordinate_region"
      },
      "street_cross": "Africa",
      "display_location": "Africa",
      "latitude": 0.0,
      "longitude": 0.0,
      "lat_long": "0.0000, 0.0000",
      "course": "Static",
      "spatial_region": "Africa",
      "observation_count": 59844,
      "source_count": 11,
      "sources": [
        "BerkeleySETI",
        "IRIS",
        "LOFAR",
        "MADIS",
        "NASADeepSpaceNetwork",
        "OpenSky",
        "RaspberryShake",
        "SETILive",
        "SatNOGS",
        "USCRN",
        "WebSDR"
      ],
      "evidence_summary": [
        "Recursive manifold density detected",
        "Temporal coherence preserved",
        "Spatial clustering present"
      ],
      "contradictions": [],
      "_convergence_passes": 2,
      "lock_direction": "\u2192",
      "lock_velocity_per_minute": null,
      "detector_count": null,
      "persistence_state": {
        "active_duration_seconds": 223177784,
        "persistence_score": 1.0,
        "trajectory_stability": 0.4,
        "field_viability": "TRANSIENT"
      },
      "verification_state": {
        "official_confirmation": false,
        "official_source": null,
        "official_record_id": null,
        "official_classification": null,
        "official_timestamp_utc": null,
        "lead_time_seconds": null,
        "magnitude_delta": null,
        "spatial_error_km": null,
        "classification_agreement": null
      },
      "cross_regime_couplings": [],
      "manifold_topology": {
        "topology_class": "Localized Recursive Compression",
        "field_density": 0.4,
        "cross_regime_density": 0.25,
        "recursive_complexity": 1.0
      },
      "estimated_energy": {
        "value": null,
        "units": "joules"
      },
      "altitude_km": null,
      "depth_km": null,
      "velocity_vector": {
        "bearing_degrees": null,
        "velocity_kmh": null
      },
      "source_lineage": [],
      "linked_observations": [
        "OBS-00000026",
        "OBS-00000027",
        "OBS-00000028",
        "OBS-00000029",
        "OBS-00000030",
        "OBS-00000031",
        "OBS-00000032",
        "OBS-00000033",
        "OBS-00000034",
        "OBS-00000035",
        "OBS-00000036",
        "OBS-00000037",
        "OBS-00000038",
        "OBS-00032383",
        "OBS-00032384",
        "OBS-00032385",
        "OBS-00032386",
        "OBS-00032387",
        "OBS-00032388",
        "OBS-00032389",
        "OBS-00032390",
        "OBS-00032391",
        "OBS-00032392",
        "OBS-00032393",
        "OBS-00032394",
        "OBS-00032395",
        "OBS-00032422",
        "OBS-00032423",
        "OBS-00032424",
        "OBS-00032425",
        "OBS-00032426",
        "OBS-00032427",
        "OBS-00032428",
        "OBS-00032429",
        "OBS-00032430",
        "OBS-00032431",
        "OBS-00032432",
        "OBS-00032433",
        "OBS-00032434",
        "OBS-00032435",
        "OBS-00032436",
        "OBS-00032437",
        "OBS-00032438",
        "OBS-00032439",
        "OBS-00032440",
        "OBS-00032441",
        "OBS-00032442",
        "OBS-00032443",
        "OBS-00032444",
        "OBS-00032445",
        "OBS-00032446",
        "OBS-00032447",
        "OBS-00032474",
        "OBS-00032475",
        "OBS-00032476",
        "OBS-00032477",
        "OBS-00032478",
        "OBS-00032479",
        "OBS-00032480",
        "OBS-00032481",
        "OBS-00032482",
        "OBS-00032483",
        "OBS-00032484",
        "OBS-00032485",
        "OBS-00032486",
        "OBS-00033256",
        "OBS-00033257",
        "OBS-00033258",
        "OBS-00033259",
        "OBS-00033260",
        "OBS-00033261",
        "OBS-00033262",
        "OBS-00033263",
        "OBS-00033264",
        "OBS-00033265",
        "OBS-00033266",
        "OBS-00033267",
        "OBS-00033268",
        "OBS-00033269",
        "OBS-00033270",
        "OBS-00033271",
        "OBS-00033272",
        "OBS-00033273",
        "OBS-00033274",
        "OBS-00033275",
        "OBS-00033276",
        "OBS-00033277",
        "OBS-00033278",
        "OBS-00033279",
        "OBS-00033618",
        "OBS-00033619",
        "OBS-00033620",
        "OBS-00033621",
        "OBS-00033623",
        "OBS-00033624",
        "OBS-00033625",
        "OBS-00033626",
        "OBS-00033629",
        "OBS-00033630",
        "OBS-00033631",
        "OBS-00033632",
        "OBS-00033634",
        "OBS-00033635",
        "OBS-00033636",
        "OBS-00033637",
        "OBS-00033638",
        "OBS-00033639",
        "OBS-00033640",
        "OBS-00033641",
        "OBS-00033642",
        "OBS-00033643",
        "OBS-00033644",
        "OBS-00033645",
        "OBS-00033646",
        "OBS-00033647",
        "OBS-00033649",
        "OBS-00033650",
        "OBS-00033651",
        "OBS-00033652",
        "OBS-00033655",
        "OBS-00033656",
        "OBS-00033657",
        "OBS-00033658",
        "OBS-00033660",
        "OBS-00033661",
        "OBS-00033662",
        "OBS-00033663",
        "OBS-00033664",
        "OBS-00033665",
        "OBS-00033666",
        "OBS-00033667",
        "OBS-00033668",
        "OBS-00033669",
        "OBS-00033670",
        "OBS-00033671",
        "OBS-00033672",
        "OBS-00033674",
        "OBS-00033675",
        "OBS-00033676",
        "OBS-00033677",
        "OBS-00033680",
        "OBS-00033681",
        "OBS-00033682",
        "OBS-00033683",
        "OBS-00033685",
        "OBS-00033686",
        "OBS-00033687",
        "OBS-00033688",
        "OBS-00033689",
        "OBS-00033690",
        "OBS-00033691",
        "OBS-00033692",
        "OBS-00033693",
        "OBS-00033694",
        "OBS-00033695",
        "OBS-00033696",
        "OBS-00033697",
        "OBS-00033698",
        "OBS-00033699",
        "OBS-00033701",
        "OBS-00033702",
        "OBS-00033703",
        "OBS-00033704",
        "OBS-00033707",
        "OBS-00033708",
        "OBS-00033709",
        "OBS-00033710",
        "OBS-00033712",
        "OBS-00033713",
        "OBS-00033714",
        "OBS-00033715",
        "OBS-00033716",
        "OBS-00033717",
        "OBS-00033718",
        "OBS-00033719",
        "OBS-00033720",
        "OBS-00033721",
        "OBS-00033722",
        "OBS-00033723",
        "OBS-00033724",
        "OBS-00033726",
        "OBS-00033727",
        "OBS-00033728",
        "OBS-00033729",
        "OBS-00033732",
        "OBS-00033733",
        "OBS-00033734",
        "OBS-00033735",
        "OBS-00033737",
        "OBS-00033738",
        "OBS-00033739",
        "OBS-00033740",
        "OBS-00033741",
        "OBS-00033742",
        "OBS-00033743",
        "OBS-00033744",
        "OBS-00033745",
        "OBS-00033746",
        "OBS-00033747",
        "OBS-00033748",
        "OBS-00033749",
        "OBS-00033751",
        "OBS-00033752",
        "OBS-00033753",
        "OBS-00033754",
        "OBS-00033757",
        "OBS-00033758",
        "OBS-00033759",
        "OBS-00033760",
        "OBS-00033762",
        "OBS-00033763",
        "OBS-00033764",
        "OBS-00033765",
        "OBS-00033766",
        "OBS-00033767",
        "OBS-00033768",
        "OBS-00033769",
        "OBS-00033770",
        "OBS-00033771",
        "OBS-00033772",
        "OBS-00033773",
        "OBS-00033774",
        "OBS-00033776",
        "OBS-00033777",
        "OBS-00033778",
        "OBS-00033779",
        "OBS-00033782",
        "OBS-00033783",
        "OBS-00033784",
        "OBS-00033785",
        "OBS-00033787",
        "OBS-00033788",
        "OBS-00033789",
        "OBS-00033790",
        "OBS-00033791",
        "OBS-00033792",
        "OBS-00033793",
        "OBS-00033794",
        "OBS-00033795",
        "OBS-00033796",
        "OBS-00033797",
        "OBS-00033798",
        "OBS-00033799",
        "OBS-00033801",
        "OBS-00033802",
        "OBS-00033803",
        "OBS-00033804",
        "OBS-00033807",
        "OBS-00033808",
        "OBS-00033809"
      ],
      "forecast_state": {
        "projection_state": "MONITOR",
        "estimated_decay_utc": "2026-05-14T11:29:37.358731+00:00",
        "forecast_confidence": 0.4
      },
      "dashboard_priority": 40.0,
      "operational_priority": "LOW",
      "operational_notes": [
        "Monitor recursive stabilization",
        "Track cross-regime emergence"
      ]
    },
    {
      "event_id": "MANI-041819-0005",
      "event_family": "SEAM_RECURSIVE_MANIFOLD",
      "acquisition_utc": "2019-04-18T05:39:53.343316+00:00",
      "first_observation_utc": "2019-04-18T05:39:53.343316+00:00",
      "last_observation_utc": "2026-05-14T07:29:53.906299+00:00",
      "pred_time_utc": "2019-04-18T06:00:53.343316+00:00",
      "lock_state": "IDLE/MONITOR (39.7%)",
      "recursive_lock": 39.7,
      "lock_thresholds": {
        "85_percent_utc": null,
        "90_percent_utc": null,
        "95_percent_utc": null
      },
      "lock_progression_seconds": {
        "85_to_90": null,
        "90_to_95": null,
        "85_to_official": null
      },
      "signature": "Bow Shock Compression",
      "signature_family": "SPACE_WEATHER",
      "signature_subclass": "Recursive Coupled Perturbation",
      "regime": "space_weather",
      "magnitude": "N/A",
      "location": {
        "country": "Africa",
        "state_region": "Africa",
        "county_area": "Africa",
        "city": null,
        "locality": "Africa",
        "street_cross": "Africa",
        "display_follow": "Africa",
        "display_target": "Africa",
        "display_lock": "Africa | 0.0000, 0.0000",
        "lat_long": "0.0000, 0.0000",
        "location_precision": "area",
        "location_source": "coordinate_region"
      },
      "street_cross": "Africa",
      "display_location": "Africa",
      "latitude": 0.0,
      "longitude": 0.0,
      "lat_long": "0.0000, 0.0000",
      "course": "Static",
      "spatial_region": "Africa",
      "observation_count": 37400,
      "source_count": 7,
      "sources": [
        "GOES",
        "GlobeAtNight",
        "NOAA_SWPC",
        "SatNOGS",
        "SloanDigitalSkySurvey",
        "StanfordSID",
        "eCallisto"
      ],
      "evidence_summary": [
        "Recursive manifold density detected",
        "Temporal coherence preserved",
        "Spatial clustering present"
      ],
      "contradictions": [],
      "_convergence_passes": 2,
      "lock_direction": "\u2192",
      "lock_velocity_per_minute": null,
      "detector_count": null,
      "persistence_state": {
        "active_duration_seconds": 223177800,
        "persistence_score": 1.0,
        "trajectory_stability": 0.4,
        "field_viability": "TRANSIENT"
      },
      "verification_state": {
        "official_confirmation": false,
        "official_source": null,
        "official_record_id": null,
        "official_classification": null,
        "official_timestamp_utc": null,
        "lead_time_seconds": null,
        "magnitude_delta": null,
        "spatial_error_km": null,
        "classification_agreement": null
      },
      "cross_regime_couplings": [],
      "manifold_topology": {
        "topology_class": "Localized Recursive Compression",
        "field_density": 0.4,
        "cross_regime_density": 0.25,
        "recursive_complexity": 1.0
      },
      "estimated_energy": {
        "value": null,
        "units": "joules"
      },
      "altitude_km": null,
      "depth_km": null,
      "velocity_vector": {
        "bearing_degrees": null,
        "velocity_kmh": null
      },
      "source_lineage": [],
      "linked_observations": [
        "OBS-00000064",
        "OBS-00000065",
        "OBS-00000066",
        "OBS-00000067",
        "OBS-00000068",
        "OBS-00000069",
        "OBS-00000070",
        "OBS-00000071",
        "OBS-00000072",
        "OBS-00000073",
        "OBS-00000074",
        "OBS-00000075",
        "OBS-00000076",
        "OBS-00000727",
        "OBS-00000728",
        "OBS-00000729",
        "OBS-00000730",
        "OBS-00000731",
        "OBS-00000732",
        "OBS-00000733",
        "OBS-00000734",
        "OBS-00000735",
        "OBS-00000736",
        "OBS-00000737",
        "OBS-00000738",
        "OBS-00000739",
        "OBS-00000740",
        "OBS-00000741",
        "OBS-00000742",
        "OBS-00000743",
        "OBS-00000744",
        "OBS-00000745",
        "OBS-00000746",
        "OBS-00000747",
        "OBS-00000748",
        "OBS-00000749",
        "OBS-00000750",
        "OBS-00000751",
        "OBS-00000752",
        "OBS-00000753",
        "OBS-00000754",
        "OBS-00000755",
        "OBS-00000756",
        "OBS-00000757",
        "OBS-00000758",
        "OBS-00000759",
        "OBS-00000760",
        "OBS-00000761",
        "OBS-00000762",
        "OBS-00000763",
        "OBS-00000764",
        "OBS-00000765",
        "OBS-00000766",
        "OBS-00000767",
        "OBS-00000768",
        "OBS-00000769",
        "OBS-00000770",
        "OBS-00000771",
        "OBS-00000772",
        "OBS-00000773",
        "OBS-00000774",
        "OBS-00000775",
        "OBS-00000776",
        "OBS-00000777",
        "OBS-00000778",
        "OBS-00000779",
        "OBS-00000780",
        "OBS-00000781",
        "OBS-00000782",
        "OBS-00000783",
        "OBS-00000784",
        "OBS-00000785",
        "OBS-00000786",
        "OBS-00000787",
        "OBS-00000788",
        "OBS-00000789",
        "OBS-00000790",
        "OBS-00000791",
        "OBS-00000792",
        "OBS-00000793",
        "OBS-00000794",
        "OBS-00000795",
        "OBS-00000796",
        "OBS-00000797",
        "OBS-00000798",
        "OBS-00000799",
        "OBS-00000800",
        "OBS-00000801",
        "OBS-00000802",
        "OBS-00000803",
        "OBS-00000804",
        "OBS-00000805",
        "OBS-00000806",
        "OBS-00000807",
        "OBS-00000808",
        "OBS-00000809",
        "OBS-00000810",
        "OBS-00000811",
        "OBS-00000812",
        "OBS-00000813",
        "OBS-00000814",
        "OBS-00000815",
        "OBS-00000816",
        "OBS-00000817",
        "OBS-00000818",
        "OBS-00000819",
        "OBS-00000820",
        "OBS-00000821",
        "OBS-00000822",
        "OBS-00000823",
        "OBS-00000824",
        "OBS-00000825",
        "OBS-00000826",
        "OBS-00000827",
        "OBS-00000828",
        "OBS-00000829",
        "OBS-00000830",
        "OBS-00000831",
        "OBS-00000832",
        "OBS-00000833",
        "OBS-00000834",
        "OBS-00000835",
        "OBS-00000836",
        "OBS-00000837",
        "OBS-00000838",
        "OBS-00000839",
        "OBS-00000840",
        "OBS-00000841",
        "OBS-00000842",
        "OBS-00000843",
        "OBS-00000844",
        "OBS-00000845",
        "OBS-00000846",
        "OBS-00000847",
        "OBS-00000848",
        "OBS-00000849",
        "OBS-00000850",
        "OBS-00000851",
        "OBS-00000852",
        "OBS-00000853",
        "OBS-00000854",
        "OBS-00000855",
        "OBS-00000856",
        "OBS-00000857",
        "OBS-00000858",
        "OBS-00000859",
        "OBS-00000860",
        "OBS-00000861",
        "OBS-00000862",
        "OBS-00000863",
        "OBS-00000864",
        "OBS-00000865",
        "OBS-00000866",
        "OBS-00000867",
        "OBS-00000868",
        "OBS-00000869",
        "OBS-00000870",
        "OBS-00000871",
        "OBS-00000872",
        "OBS-00000873",
        "OBS-00000874",
        "OBS-00000875",
        "OBS-00000876",
        "OBS-00000877",
        "OBS-00000878",
        "OBS-00000879",
        "OBS-00000880",
        "OBS-00000881",
        "OBS-00000882",
        "OBS-00000883",
        "OBS-00000884",
        "OBS-00000885",
        "OBS-00000886",
        "OBS-00000887",
        "OBS-00000888",
        "OBS-00000889",
        "OBS-00000890",
        "OBS-00000891",
        "OBS-00000892",
        "OBS-00000893",
        "OBS-00000894",
        "OBS-00000895",
        "OBS-00000896",
        "OBS-00000897",
        "OBS-00000898",
        "OBS-00000899",
        "OBS-00000900",
        "OBS-00000901",
        "OBS-00000902",
        "OBS-00000903",
        "OBS-00000904",
        "OBS-00000905",
        "OBS-00000906",
        "OBS-00000907",
        "OBS-00000908",
        "OBS-00000909",
        "OBS-00000910",
        "OBS-00000911",
        "OBS-00000912",
        "OBS-00000913",
        "OBS-00000914",
        "OBS-00000915",
        "OBS-00000916",
        "OBS-00000917",
        "OBS-00000918",
        "OBS-00000919",
        "OBS-00000920",
        "OBS-00000921",
        "OBS-00000922",
        "OBS-00000923",
        "OBS-00000924",
        "OBS-00000925",
        "OBS-00000926",
        "OBS-00000927",
        "OBS-00000928",
        "OBS-00000929",
        "OBS-00000930",
        "OBS-00000931",
        "OBS-00000932",
        "OBS-00000933",
        "OBS-00000934",
        "OBS-00000935",
        "OBS-00000936",
        "OBS-00000937",
        "OBS-00000938",
        "OBS-00000939",
        "OBS-00000940",
        "OBS-00000941",
        "OBS-00000942",
        "OBS-00000943",
        "OBS-00000944",
        "OBS-00000945",
        "OBS-00000946",
        "OBS-00000947",
        "OBS-00000948",
        "OBS-00000949",
        "OBS-00000950",
        "OBS-00000951",
        "OBS-00000952",
        "OBS-00000953",
        "OBS-00000954",
        "OBS-00000955",
        "OBS-00000956",
        "OBS-00000957",
        "OBS-00000958",
        "OBS-00000959",
        "OBS-00000960",
        "OBS-00000961",
        "OBS-00000962",
        "OBS-00000963"
      ],
      "forecast_state": {
        "projection_state": "MONITOR",
        "estimated_decay_utc": "2026-05-14T11:29:53.906299+00:00",
        "forecast_confidence": 0.4
      },
      "dashboard_priority": 39.7,
      "operational_priority": "LOW",
      "operational_notes": [
        "Monitor recursive stabilization",
        "Track cross-regime emergence"
      ]
    }
  ],
  "active_events": [
    {
      "event_id": "MANI-062324-0006",
      "event_family": "SEAM_RECURSIVE_MANIFOLD",
      "acquisition_utc": "2024-06-23T08:27:25.722409+00:00",
      "first_observation_utc": "2024-06-23T08:27:25.722409+00:00",
      "last_observation_utc": "2026-05-14T07:29:38.112581+00:00",
      "pred_time_utc": "2024-06-23T08:48:25.722409+00:00",
      "lock_state": "FOLLOW PROTOCOL (63.6%)",
      "recursive_lock": 63.6,
      "lock_thresholds": {
        "85_percent_utc": null,
        "90_percent_utc": null,
        "95_percent_utc": null
      },
      "lock_progression_seconds": {
        "85_to_90": null,
        "90_to_95": null,
        "85_to_official": null
      },
      "signature": "Crustal Pulse",
      "signature_family": "SEISMIC",
      "signature_subclass": "Recursive Coupled Perturbation",
      "regime": "seismic",
      "magnitude": "M 7.4",
      "location": {
        "country": "United States",
        "state_region": "CA",
        "county_area": "Texas / New Mexico Region",
        "city": "Redlands",
        "locality": "Redlands, CA",
        "street_cross": "6 km SSW of Redlands, CA",
        "display_follow": "Texas / New Mexico Region",
        "display_target": "Redlands, CA, United States",
        "display_lock": "Redlands, CA | 34.8050, -96.2827",
        "lat_long": "34.8050, -96.2827",
        "location_precision": "area",
        "location_source": "payload"
      },
      "street_cross": "6 km SSW of Redlands, CA",
      "display_location": "Redlands, CA, United States",
      "latitude": 34.805,
      "longitude": -96.2827,
      "lat_long": "34.8050, -96.2827",
      "course": "SW drift",
      "spatial_region": "Texas / New Mexico Region",
      "observation_count": 8092,
      "source_count": 6,
      "sources": [
        "EMSC",
        "IRIS",
        "RaspberryShake",
        "Safecast",
        "SatNOGS",
        "USGS"
      ],
      "evidence_summary": [
        "Recursive manifold density detected",
        "Temporal coherence preserved",
        "Spatial clustering present"
      ],
      "contradictions": [],
      "_convergence_passes": 2,
      "lock_direction": "\u2192",
      "lock_velocity_per_minute": null,
      "detector_count": null,
      "persistence_state": {
        "active_duration_seconds": 59612532,
        "persistence_score": 1.0,
        "trajectory_stability": 0.64,
        "field_viability": "TRANSIENT"
      },
      "verification_state": {
        "official_confirmation": false,
        "official_source": null,
        "official_record_id": null,
        "official_classification": null,
        "official_timestamp_utc": null,
        "lead_time_seconds": null,
        "magnitude_delta": null,
        "spatial_error_km": null,
        "classification_agreement": null
      },
      "cross_regime_couplings": [],
      "manifold_topology": {
        "topology_class": "Localized Recursive Compression",
        "field_density": 0.64,
        "cross_regime_density": 0.25,
        "recursive_complexity": 1.0
      },
      "estimated_energy": {
        "value": null,
        "units": "joules"
      },
      "altitude_km": null,
      "depth_km": null,
      "velocity_vector": {
        "bearing_degrees": null,
        "velocity_kmh": null
      },
      "source_lineage": [],
      "linked_observations": [
        "OBS-00000077",
        "OBS-00000127",
        "OBS-00000179",
        "OBS-00000230",
        "OBS-00000280",
        "OBS-00000330",
        "OBS-00000380",
        "OBS-00000430",
        "OBS-00000480",
        "OBS-00000530",
        "OBS-00000580",
        "OBS-00000630",
        "OBS-00000681",
        "OBS-00037324",
        "OBS-00037374",
        "OBS-00037426",
        "OBS-00037477",
        "OBS-00037527",
        "OBS-00037577",
        "OBS-00037627",
        "OBS-00037677",
        "OBS-00037727",
        "OBS-00037777",
        "OBS-00037827",
        "OBS-00037877",
        "OBS-00037928",
        "OBS-00000078",
        "OBS-00000129",
        "OBS-00000181",
        "OBS-00000232",
        "OBS-00000282",
        "OBS-00000332",
        "OBS-00000382",
        "OBS-00000432",
        "OBS-00000482",
        "OBS-00000532",
        "OBS-00000582",
        "OBS-00000632",
        "OBS-00000683",
        "OBS-00037325",
        "OBS-00037376",
        "OBS-00037428",
        "OBS-00037479",
        "OBS-00037529",
        "OBS-00037579",
        "OBS-00037629",
        "OBS-00037679",
        "OBS-00037729",
        "OBS-00037779",
        "OBS-00037829",
        "OBS-00037879",
        "OBS-00037930",
        "OBS-00000079",
        "OBS-00000130",
        "OBS-00000182",
        "OBS-00000233",
        "OBS-00000283",
        "OBS-00000333",
        "OBS-00000383",
        "OBS-00000433",
        "OBS-00000483",
        "OBS-00000533",
        "OBS-00000583",
        "OBS-00000633",
        "OBS-00000684",
        "OBS-00037326",
        "OBS-00037377",
        "OBS-00037429",
        "OBS-00037480",
        "OBS-00037530",
        "OBS-00037580",
        "OBS-00037630",
        "OBS-00037680",
        "OBS-00037730",
        "OBS-00037780",
        "OBS-00037830",
        "OBS-00037880",
        "OBS-00037931",
        "OBS-00000080",
        "OBS-00000131",
        "OBS-00000183",
        "OBS-00000234",
        "OBS-00000284",
        "OBS-00000334",
        "OBS-00000384",
        "OBS-00000434",
        "OBS-00000484",
        "OBS-00000534",
        "OBS-00000584",
        "OBS-00000634",
        "OBS-00000685",
        "OBS-00037327",
        "OBS-00037378",
        "OBS-00037430",
        "OBS-00037481",
        "OBS-00037531",
        "OBS-00037581",
        "OBS-00037631",
        "OBS-00037681",
        "OBS-00037731",
        "OBS-00037781",
        "OBS-00037831",
        "OBS-00037881",
        "OBS-00037932",
        "OBS-00000081",
        "OBS-00000132",
        "OBS-00000184",
        "OBS-00000235",
        "OBS-00000285",
        "OBS-00000335",
        "OBS-00000385",
        "OBS-00000435",
        "OBS-00000485",
        "OBS-00000535",
        "OBS-00000585",
        "OBS-00000635",
        "OBS-00000686",
        "OBS-00037328",
        "OBS-00037379",
        "OBS-00037431",
        "OBS-00037482",
        "OBS-00037532",
        "OBS-00037582",
        "OBS-00037632",
        "OBS-00037682",
        "OBS-00037732",
        "OBS-00037782",
        "OBS-00037832",
        "OBS-00037882",
        "OBS-00037933",
        "OBS-00000082",
        "OBS-00000133",
        "OBS-00000185",
        "OBS-00000236",
        "OBS-00000286",
        "OBS-00000336",
        "OBS-00000386",
        "OBS-00000436",
        "OBS-00000486",
        "OBS-00000536",
        "OBS-00000586",
        "OBS-00000636",
        "OBS-00000687",
        "OBS-00037329",
        "OBS-00037380",
        "OBS-00037432",
        "OBS-00037483",
        "OBS-00037533",
        "OBS-00037583",
        "OBS-00037633",
        "OBS-00037683",
        "OBS-00037733",
        "OBS-00037783",
        "OBS-00037833",
        "OBS-00037883",
        "OBS-00037934",
        "OBS-00000083",
        "OBS-00000134",
        "OBS-00000186",
        "OBS-00000237",
        "OBS-00000287",
        "OBS-00000337",
        "OBS-00000387",
        "OBS-00000437",
        "OBS-00000487",
        "OBS-00000537",
        "OBS-00000587",
        "OBS-00000637",
        "OBS-00000688",
        "OBS-00037330",
        "OBS-00037381",
        "OBS-00037433",
        "OBS-00037484",
        "OBS-00037534",
        "OBS-00037584",
        "OBS-00037634",
        "OBS-00037684",
        "OBS-00037734",
        "OBS-00037784",
        "OBS-00037834",
        "OBS-00037884",
        "OBS-00037935",
        "OBS-00000084",
        "OBS-00000135",
        "OBS-00000187",
        "OBS-00000238",
        "OBS-00000288",
        "OBS-00000338",
        "OBS-00000388",
        "OBS-00000438",
        "OBS-00000488",
        "OBS-00000538",
        "OBS-00000588",
        "OBS-00000638",
        "OBS-00000689",
        "OBS-00037331",
        "OBS-00037382",
        "OBS-00037434",
        "OBS-00037485",
        "OBS-00037535",
        "OBS-00037585",
        "OBS-00037635",
        "OBS-00037685",
        "OBS-00037735",
        "OBS-00037785",
        "OBS-00037835",
        "OBS-00037885",
        "OBS-00037936",
        "OBS-00000085",
        "OBS-00000137",
        "OBS-00000189",
        "OBS-00000240",
        "OBS-00000290",
        "OBS-00000340",
        "OBS-00000390",
        "OBS-00000440",
        "OBS-00000490",
        "OBS-00000540",
        "OBS-00000590",
        "OBS-00000640",
        "OBS-00000691",
        "OBS-00037332",
        "OBS-00037384",
        "OBS-00037436",
        "OBS-00037487",
        "OBS-00037537",
        "OBS-00037587",
        "OBS-00037637",
        "OBS-00037687",
        "OBS-00037737",
        "OBS-00037787",
        "OBS-00037837",
        "OBS-00037887",
        "OBS-00037938",
        "OBS-00000086",
        "OBS-00000138",
        "OBS-00000190",
        "OBS-00000241",
        "OBS-00000291",
        "OBS-00000341",
        "OBS-00000391",
        "OBS-00000441",
        "OBS-00000491",
        "OBS-00000541",
        "OBS-00000591",
        "OBS-00000641",
        "OBS-00000692",
        "OBS-00037333",
        "OBS-00037385",
        "OBS-00037437"
      ],
      "forecast_state": {
        "projection_state": "ACTIVE",
        "estimated_decay_utc": "2026-05-14T11:29:38.112581+00:00",
        "forecast_confidence": 0.64
      },
      "dashboard_priority": 63.6,
      "operational_priority": "LOW",
      "operational_notes": [
        "Monitor recursive stabilization",
        "Track cross-regime emergence"
      ]
    },
    {
      "event_id": "MANI-031421-0007",
      "event_family": "SEAM_RECURSIVE_MANIFOLD",
      "acquisition_utc": "2021-03-14T10:34:37.119920+00:00",
      "first_observation_utc": "2021-03-14T10:34:37.119920+00:00",
      "last_observation_utc": "2026-05-14T07:29:37.707894+00:00",
      "pred_time_utc": "2021-03-14T10:55:37.119920+00:00",
      "lock_state": "FOLLOW PROTOCOL (61.3%)",
      "recursive_lock": 61.3,
      "lock_thresholds": {
        "85_percent_utc": null,
        "90_percent_utc": null,
        "95_percent_utc": null
      },
      "lock_progression_seconds": {
        "85_to_90": null,
        "90_to_95": null,
        "85_to_official": null
      },
      "signature": "Radiological Drift",
      "signature_family": "RADIOLOGICAL",
      "signature_subclass": "Recursive Coupled Perturbation",
      "regime": "radiological",
      "magnitude": "106.2",
      "location": {
        "country": "Europe",
        "state_region": "Europe",
        "county_area": "Europe",
        "city": null,
        "locality": "Europe",
        "street_cross": "Europe",
        "display_follow": "Europe",
        "display_target": "Europe",
        "display_lock": "Europe | 43.1204, 38.2823",
        "lat_long": "43.1204, 38.2823",
        "location_precision": "area",
        "location_source": "coordinate_region"
      },
      "street_cross": "Europe",
      "display_location": "Europe",
      "latitude": 43.1204,
      "longitude": 38.2823,
      "lat_long": "43.1204, 38.2823",
      "course": "NW drift",
      "spatial_region": "Europe",
      "observation_count": 520,
      "source_count": 4,
      "sources": [
        "GOES",
        "NOAA_SWPC",
        "Safecast",
        "SatNOGS"
      ],
      "evidence_summary": [
        "Recursive manifold density detected",
        "Temporal coherence preserved",
        "Spatial clustering present"
      ],
      "contradictions": [],
      "_convergence_passes": 2,
      "lock_direction": "\u2192",
      "lock_velocity_per_minute": null,
      "detector_count": null,
      "persistence_state": {
        "active_duration_seconds": 163025700,
        "persistence_score": 1.0,
        "trajectory_stability": 0.61,
        "field_viability": "TRANSIENT"
      },
      "verification_state": {
        "official_confirmation": false,
        "official_source": null,
        "official_record_id": null,
        "official_classification": null,
        "official_timestamp_utc": null,
        "lead_time_seconds": null,
        "magnitude_delta": null,
        "spatial_error_km": null,
        "classification_agreement": null
      },
      "cross_regime_couplings": [],
      "manifold_topology": {
        "topology_class": "Localized Recursive Compression",
        "field_density": 0.61,
        "cross_regime_density": 0.25,
        "recursive_complexity": 0.21
      },
      "estimated_energy": {
        "value": null,
        "units": "joules"
      },
      "altitude_km": null,
      "depth_km": null,
      "velocity_vector": {
        "bearing_degrees": null,
        "velocity_kmh": null
      },
      "source_lineage": [],
      "linked_observations": [
        "OBS-00033293",
        "OBS-00033294",
        "OBS-00033295",
        "OBS-00033296",
        "OBS-00033297",
        "OBS-00033298",
        "OBS-00033299",
        "OBS-00033300",
        "OBS-00033301",
        "OBS-00033302",
        "OBS-00033303",
        "OBS-00033304",
        "OBS-00033305",
        "OBS-00033306",
        "OBS-00033307",
        "OBS-00033308",
        "OBS-00033309",
        "OBS-00033310",
        "OBS-00033311",
        "OBS-00033312",
        "OBS-00033313",
        "OBS-00033314",
        "OBS-00033315",
        "OBS-00033316",
        "OBS-00033317",
        "OBS-00033318",
        "OBS-00033319",
        "OBS-00033320",
        "OBS-00033321",
        "OBS-00033322",
        "OBS-00033323",
        "OBS-00033324",
        "OBS-00033325",
        "OBS-00033326",
        "OBS-00033327",
        "OBS-00033328",
        "OBS-00033329",
        "OBS-00033330",
        "OBS-00033331",
        "OBS-00033332",
        "OBS-00033333",
        "OBS-00033334",
        "OBS-00033335",
        "OBS-00033336",
        "OBS-00033337",
        "OBS-00033338",
        "OBS-00033339",
        "OBS-00033340",
        "OBS-00033341",
        "OBS-00033342",
        "OBS-00033343",
        "OBS-00033344",
        "OBS-00033345",
        "OBS-00033346",
        "OBS-00033347",
        "OBS-00033348",
        "OBS-00033349",
        "OBS-00033350",
        "OBS-00033351",
        "OBS-00033352",
        "OBS-00033353",
        "OBS-00033354",
        "OBS-00033355",
        "OBS-00033356",
        "OBS-00033357",
        "OBS-00033358",
        "OBS-00033359",
        "OBS-00033360",
        "OBS-00033361",
        "OBS-00033362",
        "OBS-00033363",
        "OBS-00033364",
        "OBS-00033365",
        "OBS-00033366",
        "OBS-00033367",
        "OBS-00033518",
        "OBS-00033519",
        "OBS-00033541",
        "OBS-00033520",
        "OBS-00033521",
        "OBS-00033542",
        "OBS-00033608",
        "OBS-00033522",
        "OBS-00033530",
        "OBS-00033538",
        "OBS-00033572",
        "OBS-00033580",
        "OBS-00033588",
        "OBS-00033596",
        "OBS-00033600",
        "OBS-00033601",
        "OBS-00033607",
        "OBS-00033610",
        "OBS-00033614",
        "OBS-00033523",
        "OBS-00033584",
        "OBS-00033606",
        "OBS-00033524",
        "OBS-00033526",
        "OBS-00033529",
        "OBS-00033568",
        "OBS-00033590",
        "OBS-00033611",
        "OBS-00033617",
        "OBS-00033525",
        "OBS-00033574",
        "OBS-00033527",
        "OBS-00033613",
        "OBS-00033528",
        "OBS-00033589",
        "OBS-00033615",
        "OBS-00033531",
        "OBS-00033583",
        "OBS-00033532",
        "OBS-00033535",
        "OBS-00033579",
        "OBS-00033585",
        "OBS-00033593",
        "OBS-00033533",
        "OBS-00033534",
        "OBS-00033577",
        "OBS-00033604",
        "OBS-00033536",
        "OBS-00033537",
        "OBS-00033591",
        "OBS-00033595",
        "OBS-00033539",
        "OBS-00033602",
        "OBS-00033616",
        "OBS-00033540",
        "OBS-00033543",
        "OBS-00033544",
        "OBS-00033545",
        "OBS-00033546",
        "OBS-00033547",
        "OBS-00033548",
        "OBS-00033549",
        "OBS-00033550",
        "OBS-00033551",
        "OBS-00033552",
        "OBS-00033553",
        "OBS-00033554",
        "OBS-00033555",
        "OBS-00033556",
        "OBS-00033557",
        "OBS-00033558",
        "OBS-00033559",
        "OBS-00033560",
        "OBS-00033561",
        "OBS-00033562",
        "OBS-00033563",
        "OBS-00033564",
        "OBS-00033565",
        "OBS-00033566",
        "OBS-00033567",
        "OBS-00033569",
        "OBS-00033573",
        "OBS-00033578",
        "OBS-00033599",
        "OBS-00033570",
        "OBS-00033582",
        "OBS-00033571",
        "OBS-00033576",
        "OBS-00033592",
        "OBS-00033575",
        "OBS-00033587",
        "OBS-00033603",
        "OBS-00033581",
        "OBS-00033586",
        "OBS-00033594",
        "OBS-00033605",
        "OBS-00033612",
        "OBS-00033597",
        "OBS-00033598",
        "OBS-00033609",
        "OBS-00038013",
        "OBS-00038028",
        "OBS-00038111",
        "OBS-00038126",
        "OBS-00038209",
        "OBS-00038224",
        "OBS-00038307",
        "OBS-00038322",
        "OBS-00038405",
        "OBS-00038420",
        "OBS-00038503",
        "OBS-00038518",
        "OBS-00038601",
        "OBS-00038616",
        "OBS-00038699",
        "OBS-00038714",
        "OBS-00038797",
        "OBS-00038812",
        "OBS-00038895",
        "OBS-00038910",
        "OBS-00038993",
        "OBS-00039008",
        "OBS-00039091",
        "OBS-00039106",
        "OBS-00039189",
        "OBS-00039204",
        "OBS-00039613",
        "OBS-00039628",
        "OBS-00039711",
        "OBS-00039726",
        "OBS-00039809",
        "OBS-00039824",
        "OBS-00039907",
        "OBS-00039922",
        "OBS-00040005",
        "OBS-00040020",
        "OBS-00040103",
        "OBS-00040118",
        "OBS-00040201",
        "OBS-00040216",
        "OBS-00040299",
        "OBS-00040314",
        "OBS-00040397",
        "OBS-00040412",
        "OBS-00040495",
        "OBS-00040510",
        "OBS-00040593",
        "OBS-00040608",
        "OBS-00040691",
        "OBS-00040706",
        "OBS-00040789",
        "OBS-00040804",
        "OBS-00041154",
        "OBS-00046013",
        "OBS-00050872",
        "OBS-00055731",
        "OBS-00060590",
        "OBS-00065449",
        "OBS-00070308",
        "OBS-00075167",
        "OBS-00080026",
        "OBS-00084885",
        "OBS-00089744",
        "OBS-00094603",
        "OBS-00099462",
        "OBS-00041408",
        "OBS-00046267",
        "OBS-00051126",
        "OBS-00055985",
        "OBS-00060844",
        "OBS-00065703",
        "OBS-00070562",
        "OBS-00075421",
        "OBS-00080280",
        "OBS-00085139"
      ],
      "forecast_state": {
        "projection_state": "ACTIVE",
        "estimated_decay_utc": "2026-05-14T11:29:37.707894+00:00",
        "forecast_confidence": 0.61
      },
      "dashboard_priority": 61.3,
      "operational_priority": "LOW",
      "operational_notes": [
        "Monitor recursive stabilization",
        "Track cross-regime emergence"
      ]
    }
  ]
}